emd/._cycles_support.py.swn
emd/__init__.py
emd/_cycles_support.py
emd/_sift_core.py
emd/_version.py
emd/cycles.py
emd/imftools.py
emd/logger.py
emd/plotting.py
emd/sift.py
emd/simulate.py
emd/spectra.py
emd/support.py
emd/tests/__init__.py
emd/tests/test_cycles.py
emd/tests/test_imftools.py
emd/tests/test_logger.py
emd/tests/test_sift.py
emd/tests/test_spectra.py
emd/tests/test_utils.py
emd-0.8.1.dist-info/METADATA
emd-0.8.1.dist-info/WHEEL
emd-0.8.1.dist-info/licenses/LICENSE.txt
emd-0.8.1.dist-info/RECORD
