Metadata-Version: 2.4
Name: emd
Version: 0.8.1
Summary: Empirical Mode Decomposition
Project-URL: Documentation, https://emd.readthedocs.io/
Project-URL: Source, https://gitlab.com/emd-dev/emd
Project-URL: Issue Tracker, https://gitlab.com/emd-dev/emd/-/issues
Author-email: Andrew Quinn <a.quinn@bham.ac.uk>
License-File: LICENSE.txt
Keywords: EMD,Frequency,Hilbert-Huang,Holospectrum,Non-Linear,Spectrum
Classifier: Intended Audience :: Science/Research
Classifier: License :: OSI Approved :: GNU General Public License v2 or later (GPLv2+)
Classifier: Programming Language :: Python :: 3
Classifier: Programming Language :: Python :: 3.9
Classifier: Programming Language :: Python :: 3.10
Classifier: Programming Language :: Python :: 3.11
Classifier: Programming Language :: Python :: 3.12
Classifier: Programming Language :: Python :: 3.13
Classifier: Topic :: Scientific/Engineering :: Bio-Informatics
Classifier: Topic :: Scientific/Engineering :: Information Analysis
Classifier: Topic :: Scientific/Engineering :: Mathematics
Classifier: Topic :: Software Development
Requires-Python: >=3.9
Requires-Dist: dcor
Requires-Dist: joblib
Requires-Dist: matplotlib
Requires-Dist: numba
Requires-Dist: numpy>=1.19.3
Requires-Dist: pandas
Requires-Dist: pyyaml>=5.1
Requires-Dist: scipy
Requires-Dist: sparse
Requires-Dist: tabulate
Provides-Extra: dev
Requires-Dist: build; extra == 'dev'
Requires-Dist: codespell; extra == 'dev'
Requires-Dist: coverage; extra == 'dev'
Requires-Dist: flake8; extra == 'dev'
Requires-Dist: pytest; extra == 'dev'
Requires-Dist: pytest-cov; extra == 'dev'
Requires-Dist: setuptools>=41.0.1; extra == 'dev'
Requires-Dist: twine; extra == 'dev'
Provides-Extra: doc
Requires-Dist: ipywidgets; extra == 'doc'
Requires-Dist: myst-parser; extra == 'doc'
Requires-Dist: numpydoc; extra == 'doc'
Requires-Dist: pydata-sphinx-theme; extra == 'doc'
Requires-Dist: sphinx-copybutton; extra == 'doc'
Requires-Dist: sphinx-design; extra == 'doc'
Requires-Dist: sphinx-gallery; extra == 'doc'
Requires-Dist: sphinx-togglebutton; extra == 'doc'
Provides-Extra: full
Requires-Dist: build; extra == 'full'
Requires-Dist: codespell; extra == 'full'
Requires-Dist: coverage; extra == 'full'
Requires-Dist: flake8; extra == 'full'
Requires-Dist: ipywidgets; extra == 'full'
Requires-Dist: myst-parser; extra == 'full'
Requires-Dist: numpydoc; extra == 'full'
Requires-Dist: pydata-sphinx-theme; extra == 'full'
Requires-Dist: pytest; extra == 'full'
Requires-Dist: pytest-cov; extra == 'full'
Requires-Dist: setuptools>=41.0.1; extra == 'full'
Requires-Dist: sphinx-copybutton; extra == 'full'
Requires-Dist: sphinx-design; extra == 'full'
Requires-Dist: sphinx-gallery; extra == 'full'
Requires-Dist: sphinx-togglebutton; extra == 'full'
Requires-Dist: twine; extra == 'full'
